<?xml version="1.0" encoding="utf-8" standalone="yes" ?>
<panel
 height="380"
 layout="topleft"
 name="panel_post_result"
 width="490">
 	<string
 	 name="profile_succeeded_str">
 	    Your Profile Feed has been updated!
 	</string>
 	<string
 	 name="postcard_succeeded_str">
 	    Email Sent!
 	</string>
 	<string
 	 name="inventory_succeeded_str">
 	    Saved to Inventory!
 	</string>
 	<string
 	 name="local_succeeded_str">
 	    Saved to Computer!
 	</string>
 	<string
 	 name="profile_failed_str">
 	    Failed to update your Profile Feed.
 	</string>
 	<string
 	 name="postcard_failed_str">
 	    Failed to send email.
 	</string>
 	<string
 	 name="inventory_failed_str">
 	    Failed to save to inventory.
 	</string>
 	<string
 	 name="local_failed_str">
 	    Failed to save to computer.
 	</string>
    <text
     follows="top|left|right"
     font="SansSerif"
     halign="center"
     height="30"
     layout="topleft"
     left="20"
     length="1"
     name="result_lbl"
     right="-20"
     type="string"
     top="100"
     word_wrap="true">
        Result
    </text>
    <button
     follows="left|top"
     height="22"
     label="Done, Close This Window"
     layout="topleft"
     left="10"
     name="close_btn"
     top_pad="10"
     width="160">
        <commit_callback
         function="Snapshot.Result.Close" />
    </button>
    <button
     follows="right|top"
     height="22"
     label="Main Menu"
     layout="topleft"
     name="back_btn"
     right="-10"
     top_delta="0"
     width="80">
        <commit_callback
         function="Snapshot.Result.Back" />
    </button>
</panel>
