<?xml version="1.0" encoding="utf-8" standalone="yes" ?>
<floater name="Post-Process Floater" title="PARAMÈTRES POST-TRAITEMENT">
	<tab_container name="Post-Process Tabs">
		<panel label="Filtre couleur" name="wmiColorFilterPanel">
			<check_box label="Activer" name="wmiColorFilterToggle" />
			<text name="wmiColorFilterBrightnessText">
				Luminosité
			</text>
			<text name="wmiColorFilterSaturationText">
				Saturation
			</text>
			<text name="wmiColorFilterContrastText">
				Contraste
			</text>
			<text name="wmiColorFilterBaseText">
				Couleur de base du contraste
			</text>
			<slider label="R" name="wmiColorFilterBaseR" />
			<slider label="V" name="wmiColorFilterBaseG" />
			<slider label="B" name="wmiColorFilterBaseB" />
			<slider label="I" name="wmiColorFilterBaseI" />
		</panel>
		<panel label="Vision de nuit" name="wmiNightVisionPanel">
			<check_box label="Activer" name="wmiNightVisionToggle" />
			<text name="wmiNightVisionBrightMultText">
				Multiple d&apos;amplificateur de lumière
			</text>
			<text name="wmiNightVisionNoiseSizeText">
				Taille du bruit
			</text>
			<text name="wmiNightVisionNoiseStrengthText">
				Force du bruit
			</text>
		</panel>
		<panel label="Éclat" name="wmiBloomPanel">
			<check_box label="Activer" name="wmiBloomToggle" />
			<text name="wmiBloomExtractText">
				Extraction de la luminosité
			</text>
			<text name="wmiBloomSizeText">
				Taille de l&apos;éclat
			</text>
			<text name="wmiBloomStrengthText">
				Force de l&apos;éclat
			</text>
		</panel>
		<panel label="Extras" name="Extras">
			<button label="Charger effet" label_selected="Charger effet" name="PPLoadEffect" />
			<button label="Enregistrer effet" label_selected="Enregistrer effet"
			     name="PPSaveEffect" />
			<line_editor label="Nom de l&apos;effet" name="PPEffectNameEditor" />
		</panel>
	</tab_container>
</floater>
