<?xml version="1.0" encoding="utf-8"?>
<panel name="panel_twitter_account">
	<string name="twitter_connected" value="Vous êtes connecté(e) à Twitter en tant que :"/>
	<string name="twitter_disconnected" value="Pas connecté(e) à Twitter"/>
	<text name="account_caption_label">
		Pas connecté(e) à Twitter.
	</text>
	<panel name="panel_buttons">
		<button label="Connexion..." name="connect_btn"/>
		<button label="Déconnexion" name="disconnect_btn"/>
		<text name="account_learn_more_label">
			[http://community.secondlife.com/t5/English-Knowledge-Base/Second-Life-Share-Twitter/ta-p/2435453 Apprenez comment publier sur Twitter]
		</text>
	</panel>
</panel>
