<llsd>
    <array>
        <array>
            <string>linearize</string>
            <real>0.0</real>
            <real>1.0</real>
            <real>1.0</real>
            <real>1.0</real>
        </array>
        <array>
            <string>stencil</string>
            <string>scanlines</string>
            <string>add-back</string>
            <real>0.0</real>
            <real>1.0</real>
            <real>0.015</real>
            <real>0</real>
        </array>
        <array>
            <string>gamma</string>
            <real>0.5</real>
            <real>1.0</real>
            <real>1.0</real>
            <real>1.0</real>
        </array>
        <array>
            <string>blur</string>
        </array>
    </array>
</llsd>