<?xml version="1.0" encoding="utf-8" standalone="yes"?>
<panel label="プロフィール" name="panel_profile">
	<string name="CaptionTextAcctInfo">
		[ACCTTYPE]
[PAYMENTINFO] [AGEVERIFICATION]
	</string>
	<string name="payment_update_link_url">
		http://www.secondlife.com/account/billing.php?lang=ja
	</string>
	<string name="partner_edit_link_url">
		http://www.secondlife.com/account/billing.php?lang=ja
	</string>
	<string name="my_account_link_url" value="http://secondlife.com/account"/>
	<string name="no_partner_text" value="なし"/>
	<string name="no_group_text" value="なし"/>
	<string name="RegisterDateFormat">
		[REG_DATE] ([AGE])
	</string>
	<layout_stack name="layout">
		<layout_panel name="profile_stack">
			<scroll_container name="profile_scroll">
				<panel name="scroll_content_panel">
					<panel name="second_life_image_panel">
						<icon label="" name="2nd_life_edit_icon" tool_tip="下の「プロフィールの編集」ボタンを押して画像を変更します"/>
						<text name="title_sl_descr_text" value="[SECOND_LIFE]："/>
					</panel>
					<panel name="first_life_image_panel">
						<icon label="" name="real_world_edit_icon" tool_tip="下の「プロフィールの編集」ボタンを押して画像を変更します"/>
						<text name="title_rw_descr_text" value="現実世界："/>
					</panel>
					<text name="title_member_text" value="メンバー登録："/>
					<text name="title_acc_status_text" value="アカウントの状態："/>
					<text name="acc_status_text">
						住人。 支払情報未登録。
              リンデン。
					</text>
					<text name="title_partner_text" value="パートナー："/>
					<text name="title_groups_text" value="グループ："/>
				</panel>
			</scroll_container>
		</layout_panel>
		<layout_panel name="profile_me_buttons_panel">
			<button label="プロフィールの編集" name="edit_profile_btn" tool_tip="個人的な情報を編集します"/>
			<button label="容姿の編集" name="edit_appearance_btn" tool_tip="見た目を作成・編集します： （身体的データ、衣類など）"/>
		</layout_panel>
	</layout_stack>
</panel>
