<?xml version="1.0" encoding="utf-8" standalone="yes"?>
<floater name="modal container" title="">
	<floater.string name="real_url">
		http://secondlife.com/app/tos/
	</floater.string>
	<floater.string name="loading_url">
		data:text/html,%3Chtml%3E%3Chead%3E%3C/head%3E%3Cbody text=%22000000%22%3E%3Ch2%3E Ładowanie %3Ca%20target%3D%22_external%22%20href%3D%22http%3A//secondlife.com/app/tos/%22%3EWarunki%20Serwisu%3C/a%3E...%3C/h2%3E %3C/body%3E %3C/html%3E
	</floater.string>
	<button label="Kontynuuj" label_selected="Kontynuuj" name="Continue"/>
	<button label="Anuluj" label_selected="Anuluj" name="Cancel"/>
	<check_box label="Zgadzam się na Warunki Serwisu (Terms of Service) i Politykę Prywatności (Privacy Policy)" name="agree_chk"/>
	<text name="tos_heading">
		Proszę dokładnie przeczytać następujące Warunki Serwisu (Terms of Service) i Politykę Prywatności (Privacy Policy). Musisz zaakceptować umowę żeby kontynuować logowanie do [SECOND_LIFE].
	</text>
</floater>
