<?xml version="1.0" encoding="utf-8" standalone="yes" ?>
<floater name="Give Money">
	<string name="payee_group">
		Zapłać grupie
	</string>
	<string name="payee_resident">
		Zapłać Rezydentowi
	</string>
	<button label="1L$" label_selected="1L$" name="fastpay 1" />
	<button label="5L$" label_selected="5L$" name="fastpay 5" />
	<button label="10L$" label_selected="10L$" name="fastpay 10" />
	<button label="20L$" label_selected="20L$" name="fastpay 20" />
	<text name="amount text">
		lub wpisz kwotę:
	</text>
	<button label="Zapłać" label_selected="Zapłać" name="pay btn" />
	<button label="Anuluj" label_selected="Anuluj" name="cancel btn" />
</floater>
