<?xml version="1.0" encoding="utf-8" standalone="yes"?>
<floater name="Snapshot" title="Foto">
	<floater.string name="unknown">
		ukendt
	</floater.string>
	<button label="Tag nyt foto" name="new_snapshot_btn"/>
	<line_editor label="Beskrivelse" name="description"/>
	<button label="Del foto" name="share"/>
	<button label="Del på internettet" name="share_to_web"/>
	<button label="Gem til beholdning" name="save_to_inventory"/>
	<button label="Gem foto" name="save"/>
	<button label="Email foto" name="share_to_email"/>
	<button label="Gem på computer" name="save_to_computer"/>
	<button label="Sæt som profil billede" name="set_profile_pic"/>
	<button label="Tilbage" name="cancel"/>
</floater>
