<?xml version="1.0" encoding="utf-8"?>
<panel name="panel_facebook_status">
	<string name="facebook_connected" value="Вы подключились к Facebook как:"/>
	<string name="facebook_disconnected" value="Не подключено к Facebook"/>
	<text name="account_caption_label">
		Не подключено к Facebook.
	</text>
	<panel name="panel_buttons">
		<button label="Подключение..." name="connect_btn"/>
		<button label="Отключить" name="disconnect_btn"/>
		<text name="account_learn_more_label">
			[http://community.secondlife.com/t5/English-Knowledge-Base/Second-Life-Share-Facebook/ta-p/2149711 О публикации в Facebook]
		</text>
	</panel>
	<text name="status_caption_label">
		О чем вы думаете?
	</text>
	<button label="Опубликовать" name="post_status_btn"/>
	<button label="Отмена" name="cancel_status_btn"/>
</panel>
